{"schemaVersion":2,"year":1000,"label":"Um 1000 — Ottonisches Reich","blurb":"Das ottonische Reich gliedert sich in die großen Stammesherzogtümer. Kaiser Otto III. träumt von der Erneuerung des Römischen Reiches.","view":{"bounds":[[46.0,4.0],[56.0,19.5]],"minZoom":4,"maxZoom":9},"layers":{"territories":"layers/territories/1000.geojson","settlements":"layers/settlements/1000.json","cultures":"layers/cultures/1000.geojson"},"factionIds":["hre","boehmen","polen","ungarn","arelat","daenemark","kroatien","frankreich","champagne","venedig"]}