{"schemaVersion":3,"year":1250,"label":"Um 1250 — Ende der Staufer","blurb":"Ende der Staufer; Beginn des Interregnums","view":{"bounds":[[43.0,-5.0],[58.5,27.0]],"minZoom":3,"maxZoom":9},"layers":{"territories":"layers/territories/1250.geojson"},"factionIds":["hre","deutschorden","boehmen","hb_mongol_empire","norwegen","ungarn","hb_crown_of_castile","hb_kingdom_of_england","schweden","hb_nicaean_empire","hb_grand_duchy_of_lithuania","frankreich","hb_icelandic_commonwealth","hb_sultanate_of_rum","hb_mamluk_sultanate","hb_hafsid_dynasty","daenemark","polen","hb_zayyanid_dynasty","hb_crown_of_aragon","hb_second_bulgarian_empire","hb_zengid_dynasty","hb_kingdom_of_sicily","hb_kingdom_of_portugal","hb_kingdom_of_alba","hb_kingdom_of_serbia","hb_despotate_of_epirus","hb_armenian_kingdom_of_cilicia","hb_marinid_sultanate","hb_duchy_of_brittany","hb_duchy_of_masovia","hb_emirate_of_granada","hb_viking_settlements","champagne","hb_republic_of_pisa","hb_capetian_house_of_anjou","arelat","hb_banate_of_bosnia","hb_county_of_auvergne","venedig","hb_duchy_of_g_og_w","hb_principality_of_achaea","hb_kingdom_of_gwynedd","hb_papal_states","schlesien","hb_abbasid_caliphate","hb_empire_of_trebizond","hb_county_of_nevers","hb_county_of_p_rigord","hb_county_of_flanders","hb_county_of_touraine","hb_kingdom_of_cyprus","hb_kingdom_of_navarre","hb_duchy_of_aquitaine","hb_county_of_bl_is","hb_county_of_artois","hb_kingdom_of_mann","hb_duchy_of_athens","hb_giudicato_of_logudoro","hb_county_of_armagnac","genua","hb_principality_of_antioch","hb_county_of_foix","hb_giudicato_of_arborea","hb_latin_empire","hb_county_of_tripoli","hb_duchy_of_the_archipelago","hb_almohad_caliphate","hb_county_of_ampuria","hb_county_of_boulogne"]}